QimenQiwu/Dockerfile
QimenQiwu/README.md
QimenQiwu/__init__.py
QimenQiwu/__main__.py
QimenQiwu/file.pdf
QimenQiwu/index.html
qimen_qiwu-2022.10.7.1.dist-info/METADATA
qimen_qiwu-2022.10.7.1.dist-info/WHEEL
qimen_qiwu-2022.10.7.1.dist-info/entry_points.txt
qimen_qiwu-2022.10.7.1.dist-info/top_level.txt
qimen_qiwu-2022.10.7.1.dist-info/RECORD
